wootrade_sdk/__init__.py
wootrade_sdk/authentication.py
wootrade_sdk/client.py
wootrade_sdk/enums.py
wootrade_sdk/exceptions.py
wootrade_sdk/helpers.py
wootrade_sdk/streams.py
wootrade_sdk/threaded_stream.py
wootrade_sdk-0.1.2.dist-info/METADATA
wootrade_sdk-0.1.2.dist-info/WHEEL
wootrade_sdk-0.1.2.dist-info/RECORD
