Metadata-Version: 2.1
Name: wootrade-sdk
Version: 0.1.2
Summary: 
Author: Akagi201
Author-email: akagi201@gmail.com
Requires-Python: >=3.10,<4.0
Classifier: Programming Language :: Python :: 3
Classifier: Programming Language :: Python :: 3.10
Classifier: Programming Language :: Python :: 3.11
Classifier: Programming Language :: Python :: 3.12
Requires-Dist: aiohttp (>=3.9.1,<4.0.0)
Requires-Dist: black (>=23.12.1,<24.0.0)
Requires-Dist: pytest (>=7.4.4,<8.0.0)
Requires-Dist: requests (>=2.31.0,<3.0.0)
Requires-Dist: websockets (>=12.0,<13.0)
